osy
