Metadata-Version: 2.1
Name: osy
Version: 0.2.4
Summary: description
Author: __token__
Author-email: skip@mail.ru
Requires-Dist: setuptools
